MANIFEST.in
README.txt
setup.py
docs/HISTORY.txt
docs/LICENSE.txt
src/silva/__init__.py
src/silva.core.layout.egg-info/PKG-INFO
src/silva.core.layout.egg-info/SOURCES.txt
src/silva.core.layout.egg-info/dependency_links.txt
src/silva.core.layout.egg-info/namespace_packages.txt
src/silva.core.layout.egg-info/not-zip-safe
src/silva.core.layout.egg-info/requires.txt
src/silva.core.layout.egg-info/top_level.txt
src/silva/core/__init__.py
src/silva/core/layout/__init__.py
src/silva/core/layout/configure.zcml
src/silva/core/layout/customization.png
src/silva/core/layout/customization.py
src/silva/core/layout/default.py
src/silva/core/layout/helpers.py
src/silva/core/layout/interfaces.py
src/silva/core/layout/lookup.py
src/silva/core/layout/markers.png
src/silva/core/layout/markers.py
src/silva/core/layout/metadata.py
src/silva/core/layout/traverser.py
src/silva/core/layout/utils.py
src/silva/core/layout/customization_templates/managecustomtemplates.pt
src/silva/core/layout/customization_templates/manageviewtemplate.pt
src/silva/core/layout/jquery/__init__.py
src/silva/core/layout/jquery/interfaces.py
src/silva/core/layout/martiansupport/__init__.py
src/silva/core/layout/martiansupport/interfaces.py
src/silva/core/layout/porto/__init__.py
src/silva/core/layout/porto/errors.py
src/silva/core/layout/porto/interfaces.py
src/silva/core/layout/porto/porto.py
src/silva/core/layout/porto/errors_templates/notfoundpage.pt
src/silva/core/layout/porto/errors_templates/othererrorpage.pt
src/silva/core/layout/porto/errors_templates/unauthorizedpage.pt
src/silva/core/layout/porto/porto_templates/breadcrumbs.cpt
src/silva/core/layout/porto/porto_templates/favicon.cpt
src/silva/core/layout/porto/porto_templates/footer.cpt
src/silva/core/layout/porto/porto_templates/header.cpt
src/silva/core/layout/porto/porto_templates/layout.cpt
src/silva/core/layout/porto/porto_templates/mainlayout.cpt
src/silva/core/layout/porto/porto_templates/navigation.cpt
src/silva/core/layout/porto/static/favicon.ico
src/silva/core/layout/porto/static/porto.css
src/silva/core/layout/porto/static/silva.css
src/silva/core/layout/tests/__init__.py
src/silva/core/layout/tests/test_customization.py
src/silva/core/layout/tests/test_errors.py
src/silva/core/layout/tests/test_grok.py
src/silva/core/layout/tests/test_markers.py
