Metadata-Version: 1.1
Name: silva.core.layout
Version: 3.0.2
Summary: Layout and theme engine for Silva CMS
Home-page: https://github.com/silvacms/silva.core.layout
Author: Infrae
Author-email: info@infrae.com
License: BSD
Keywords: layout silva core
Platform: UNKNOWN
Classifier: Framework :: Zope2
Classifier: License :: OSI Approved :: BSD License
Classifier: Programming Language :: Python
Classifier: Topic :: Software Development :: Libraries :: Python Modules
